beads_mc/__init__.py
beads_mc/config.py
beads_mc/metropolis_hastings.py
beads_mc/trait.py
beads_mc/utils.py
beads_mc/visualize.py
beads_mc-1.0.0.dist-info/METADATA
beads_mc-1.0.0.dist-info/WHEEL
beads_mc-1.0.0.dist-info/top_level.txt
beads_mc-1.0.0.dist-info/RECORD
